Megaxdl/__init__.py
Megaxdl/crypto.py
Megaxdl/errors.py
Megaxdl/mega.py
megaxdl-0.0.11.dist-info/LICENSE
megaxdl-0.0.11.dist-info/METADATA
megaxdl-0.0.11.dist-info/WHEEL
megaxdl-0.0.11.dist-info/top_level.txt
megaxdl-0.0.11.dist-info/RECORD
