Metadata-Version: 2.1
Name: megaxdl
Version: 0.0.11
Requires-Python: ~=3.10
License-File: LICENSE
Requires-Dist: tenacity >=8.2.2
Requires-Dist: requests >=2.27.1
Requires-Dist: pycryptodome <4.0.0,>=3.20.0
